masterai_scrapy_command/__init__.py
masterai_scrapy_command/crawl_with_settings.py
masterai_scrapy_command/report.py
masterai_scrapy_command-24.7.5.dist-info/METADATA
masterai_scrapy_command-24.7.5.dist-info/WHEEL
masterai_scrapy_command-24.7.5.dist-info/entry_points.txt
masterai_scrapy_command-24.7.5.dist-info/top_level.txt
masterai_scrapy_command-24.7.5.dist-info/RECORD
